{
  "type": "all",
  "limit": 50,
  "filters": {
    "status": "",
    "dateFrom": "",
    "dateTo": "",
    "consumerDid": "",
    "providerDid": "",
    "crossBorder": ""
  },
  "transfers": [
    {
      "providerCountryCode": "DE",
      "consumerComplianceName": "Ir. Johan van Dijk",
      "consumerCountryCode": "NL",
      "edcTransferId": "edc-trn-m3n4o5p6",
      "transferDate": "2026-03-10",
      "protocol": "HTTP-PULL",
      "providerComplianceName": "Dr. Petra Müller",
      "assetId": "dataset:synthea-fhir-r4-mvd",
      "providerComplianceEmail": "dpo@alpha-klinik.de",
      "crossBorder": true,
      "id": "trn-004",
      "accessLogCount": 0,
      "providerName": "AlphaKlinik Berlin",
      "providerDid": "did:web:alpha-klinik.de:participant",
      "timestamp": "2026-03-10T08:00:00Z",
      "direction": "INCOMING",
      "accessCount": 0,
      "providerCountry": "DE",
      "legalBasis": "EHDS Art. 7",
      "purposeOfSharing": "T2D FHIR cohort for Limburg clinical integration pilot",
      "edcConsumerEndpoint": "https://edc.lmc.nl:8443/api/v1/dsp",
      "edcProviderEndpoint": "https://edc.alpha-klinik.de:8443/api/v1/dsp",
      "contentHash": "2380e1c31e47ec3f12a4f7954603331d",
      "consumerComplianceEmail": "fg@lmc.nl",
      "asset": "T2D Patient Journey Dataset (FHIR R4)",
      "consumerDid": "did:web:lmc.nl:clinic",
      "consumerName": "Limburg Medical Centre",
      "consumerCountry": "NL",
      "status": "IN_PROGRESS"
    },
    {
      "providerCountryCode": "DE",
      "consumerComplianceName": "Dr. Claire Martin",
      "byteSize": 0,
      "consumerCountryCode": "FR",
      "edcTransferId": "edc-trn-q7r8s9t0",
      "transferDate": "2026-02-18",
      "protocol": "HTTP-PUSH",
      "providerComplianceName": "Dr. Petra Müller",
      "assetId": "dataset:synthea-fhir-r4-mvd",
      "providerComplianceEmail": "dpo@alpha-klinik.de",
      "crossBorder": true,
      "id": "trn-005",
      "accessLogCount": 0,
      "providerName": "AlphaKlinik Berlin",
      "providerDid": "did:web:alpha-klinik.de:participant",
      "timestamp": "2026-02-18T21:03:00Z",
      "direction": "INCOMING",
      "accessCount": 0,
      "providerCountry": "DE",
      "errorMessage": "Data integrity check failed: SHA-256 mismatch",
      "legalBasis": "EHDS Art. 7",
      "purposeOfSharing": "Cross-border T2D research transfer attempt (checksum error)",
      "edcConsumerEndpoint": "https://edc.irs.fr:8443/api/v1/dsp",
      "edcProviderEndpoint": "https://edc.alpha-klinik.de:8443/api/v1/dsp",
      "contentHash": "c414ac00dbd91a9a562a02ed13bcfd44",
      "consumerComplianceEmail": "dpo@irs.fr",
      "asset": "T2D Patient Journey Dataset (FHIR R4)",
      "consumerDid": "did:web:irs.fr:hdab",
      "consumerName": "Institut de Recherche Santé",
      "consumerCountry": "FR",
      "status": "ERROR"
    },
    {
      "providerCountryCode": "NL",
      "consumerComplianceName": "Dr. Anneliese Weber",
      "byteSize": 9876543,
      "consumerCountryCode": "DE",
      "edcTransferId": "edc-trn-i9j0k1l2",
      "transferDate": "2026-02-08",
      "protocol": "HTTP-PUSH",
      "providerComplianceName": "Ir. Johan van Dijk",
      "assetId": "dataset:prostate-cancer-registry",
      "providerComplianceEmail": "fg@lmc.nl",
      "crossBorder": true,
      "id": "trn-003",
      "accessLogCount": 2,
      "providerName": "Limburg Medical Centre",
      "providerDid": "did:web:lmc.nl:clinic",
      "timestamp": "2026-02-08T13:20:00Z",
      "direction": "OUTGOING",
      "accessCount": 2,
      "providerCountry": "NL",
      "legalBasis": "EHDS Art. 7",
      "purposeOfSharing": "Cross-border prostate cancer registry for HDAB regulatory review",
      "edcConsumerEndpoint": "https://edc.medreg.de:8443/api/v1/dsp",
      "edcProviderEndpoint": "https://edc.lmc.nl:8443/api/v1/dsp",
      "contentHash": "ad4f54bbcaadda237422bcf780149fc5",
      "contractId": "contract-pca-de-nl-003",
      "consumerComplianceEmail": "data-governance@medreg.de",
      "asset": "Prostate Cancer Registry 2024",
      "consumerDid": "did:web:medreg.de:hdab",
      "consumerName": "MedReg DE",
      "consumerCountry": "DE",
      "status": "COMPLETED"
    },
    {
      "providerCountryCode": "DE",
      "consumerComplianceName": "Thomas Becker",
      "byteSize": 43102208,
      "consumerCountryCode": "DE",
      "edcTransferId": "edc-trn-e5f6g7h8",
      "transferDate": "2026-01-29",
      "protocol": "HTTP-PULL",
      "providerComplianceName": "Dr. Petra Müller",
      "assetId": "dataset:omop-cdm-v54-analytics",
      "providerComplianceEmail": "dpo@alpha-klinik.de",
      "crossBorder": false,
      "id": "trn-002",
      "accessLogCount": 7,
      "providerName": "AlphaKlinik Berlin",
      "providerDid": "did:web:alpha-klinik.de:participant",
      "timestamp": "2026-01-29T09:45:00Z",
      "direction": "OUTGOING",
      "accessCount": 7,
      "providerCountry": "DE",
      "legalBasis": "EHDS Art. 53(c)",
      "purposeOfSharing": "OMOP CDM analytics for pharmacovigilance and drug safety",
      "edcConsumerEndpoint": "https://edc.pharmaco.de:8443/api/v1/dsp",
      "edcProviderEndpoint": "https://edc.alpha-klinik.de:8443/api/v1/dsp",
      "contentHash": "cc9569b86f2a6c8f863eb76569386b75",
      "contractId": "contract-omop-analytics-002",
      "consumerComplianceEmail": "compliance@pharmaco.de",
      "asset": "OMOP CDM v5.4 Analytics Cohort",
      "consumerDid": "did:web:pharmaco.de:research",
      "consumerName": "PharmaCo Research AG",
      "consumerCountry": "DE",
      "status": "COMPLETED"
    },
    {
      "providerCountryCode": "DE",
      "consumerComplianceName": "Thomas Becker",
      "byteSize": 14827392,
      "consumerCountryCode": "DE",
      "edcTransferId": "edc-trn-a1b2c3d4",
      "transferDate": "2026-01-23",
      "protocol": "HTTP-PUSH",
      "providerComplianceName": "Dr. Petra Müller",
      "assetId": "dataset:synthea-fhir-r4-mvd",
      "providerComplianceEmail": "dpo@alpha-klinik.de",
      "crossBorder": false,
      "id": "trn-001",
      "accessLogCount": 4,
      "providerName": "AlphaKlinik Berlin",
      "providerDid": "did:web:alpha-klinik.de:participant",
      "timestamp": "2026-01-23T16:00:00Z",
      "direction": "OUTGOING",
      "accessCount": 4,
      "providerCountry": "DE",
      "legalBasis": "EHDS Art. 53(c)",
      "purposeOfSharing": "Scientific research on Type 2 Diabetes therapeutic outcomes",
      "edcConsumerEndpoint": "https://edc.pharmaco.de:8443/api/v1/dsp",
      "edcProviderEndpoint": "https://edc.alpha-klinik.de:8443/api/v1/dsp",
      "contentHash": "8dcd34e7c1179cdb4a70ddcb1c02e0f6",
      "contractId": "contract-fhir-t2d-001",
      "consumerComplianceEmail": "compliance@pharmaco.de",
      "asset": "T2D Patient Journey Dataset (FHIR R4)",
      "consumerDid": "did:web:pharmaco.de:research",
      "consumerName": "PharmaCo Research AG",
      "consumerCountry": "DE",
      "status": "COMPLETED"
    }
  ],
  "negotiations": [
    {
      "providerCountryCode": "DE",
      "consumerComplianceName": "Ir. Johan van Dijk",
      "consumerCountryCode": "NL",
      "providerComplianceName": "Dr. Petra Müller",
      "policyRetentionDays": 180,
      "assetId": "dataset:synthea-fhir-r4-mvd",
      "providerComplianceEmail": "dpo@alpha-klinik.de",
      "consumerEdcEndpoint": "https://edc.lmc.nl:8443/api/v1/dsp",
      "crossBorder": true,
      "policyLegalBasis": "EHDS Art. 7 — cross-border data access under HDAB oversight",
      "id": "neg-005",
      "policyDataMinimisation": true,
      "accessLogCount": 0,
      "providerName": "AlphaKlinik Berlin",
      "providerDid": "did:web:alpha-klinik.de:participant",
      "timestamp": "2026-03-05T10:00:00Z",
      "accessCount": 0,
      "policyPurpose": "T2D FHIR cohort for Limburg clinical integration pilot",
      "policyProhibitedUses": "re-identification,commercial-exploitation,insurance-decisions",
      "providerCountry": "DE",
      "providerEdcEndpoint": "https://edc.alpha-klinik.de:8443/api/v1/dsp",
      "negotiationDate": "2026-03-05",
      "contentHash": "206d4c0df74dcd5a6164d1f3e35d1990",
      "policyId": "policy:ehds-cross-border-art7",
      "consumerComplianceEmail": "fg@lmc.nl",
      "asset": "T2D Patient Journey Dataset (FHIR R4)",
      "consumerDid": "did:web:lmc.nl:clinic",
      "policyPermittedUses": "clinical-care-integration,statistics,scientific-research",
      "consumerName": "Limburg Medical Centre",
      "consumerCountry": "NL",
      "status": "IN_PROGRESS"
    },
    {
      "providerCountryCode": "DE",
      "consumerComplianceName": "Dr. Claire Martin",
      "consumerCountryCode": "FR",
      "providerComplianceName": "Thomas Becker",
      "policyRetentionDays": 0,
      "assetId": "dataset:omop-cdm-v54-analytics",
      "providerComplianceEmail": "compliance@pharmaco.de",
      "terminatedReason": "Policy mismatch: usage purpose not permitted",
      "consumerEdcEndpoint": "https://edc.irs.fr:8443/api/v1/dsp",
      "crossBorder": true,
      "policyLegalBasis": "EHDS Art. 53(c) — request denied: usage purpose mismatch",
      "id": "neg-004",
      "policyDataMinimisation": true,
      "accessLogCount": 0,
      "providerName": "PharmaCo Research AG",
      "providerDid": "did:web:pharmaco.de:research",
      "timestamp": "2026-02-10T11:45:00Z",
      "accessCount": 0,
      "policyPurpose": "OMOP analytics for cross-border research collaboration (terminated)",
      "policyProhibitedUses": "re-identification,commercial-exploitation",
      "providerCountry": "DE",
      "providerEdcEndpoint": "https://edc.pharmaco.de:8443/api/v1/dsp",
      "negotiationDate": "2026-02-10",
      "contentHash": "369b3a79e3f1d552f399dee73441a83c",
      "policyId": "policy:ehds-research-use-53c",
      "consumerComplianceEmail": "dpo@irs.fr",
      "asset": "OMOP CDM v5.4 Analytics Cohort",
      "consumerDid": "did:web:irs.fr:hdab",
      "policyPermittedUses": "scientific-research",
      "consumerName": "Institut de Recherche Santé",
      "consumerCountry": "FR",
      "status": "TERMINATED"
    },
    {
      "providerCountryCode": "NL",
      "consumerComplianceName": "Dr. Anneliese Weber",
      "consumerCountryCode": "DE",
      "providerComplianceName": "Ir. Johan van Dijk",
      "policyRetentionDays": 90,
      "assetId": "dataset:prostate-cancer-registry",
      "providerComplianceEmail": "fg@lmc.nl",
      "consumerEdcEndpoint": "https://edc.medreg.de:8443/api/v1/dsp",
      "crossBorder": true,
      "policyLegalBasis": "EHDS Art. 7 — cross-border access by HDAB",
      "id": "neg-003",
      "policyDataMinimisation": true,
      "accessLogCount": 0,
      "providerName": "Limburg Medical Centre",
      "providerDid": "did:web:lmc.nl:clinic",
      "timestamp": "2026-02-04T08:30:00Z",
      "accessCount": 2,
      "policyPurpose": "Cross-border prostate cancer registry access for MedReg DE regulatory review",
      "policyProhibitedUses": "re-identification,commercial-exploitation,insurance-decisions",
      "providerCountry": "NL",
      "providerEdcEndpoint": "https://edc.lmc.nl:8443/api/v1/dsp",
      "negotiationDate": "2026-02-04",
      "lastAccessAt": "2026-02-20T11:00:00Z",
      "contentHash": "cb641c0f9a2c3c373c936958d531efc9",
      "policyId": "policy:ehds-cross-border-art7",
      "contractId": "contract-pca-de-nl-003",
      "consumerComplianceEmail": "data-governance@medreg.de",
      "asset": "Prostate Cancer Registry 2024",
      "consumerDid": "did:web:medreg.de:hdab",
      "policyPermittedUses": "regulatory-review,public-health-monitoring,statistics",
      "consumerName": "MedReg DE",
      "consumerCountry": "DE",
      "status": "CONFIRMED"
    },
    {
      "providerCountryCode": "DE",
      "consumerComplianceName": "Thomas Becker",
      "consumerCountryCode": "DE",
      "providerComplianceName": "Dr. Petra Müller",
      "policyRetentionDays": 365,
      "assetId": "dataset:omop-cdm-v54-analytics",
      "providerComplianceEmail": "dpo@alpha-klinik.de",
      "consumerEdcEndpoint": "https://edc.pharmaco.de:8443/api/v1/dsp",
      "crossBorder": false,
      "policyLegalBasis": "EHDS Art. 53(c) — scientific research",
      "id": "neg-002",
      "policyDataMinimisation": true,
      "accessLogCount": 0,
      "providerName": "AlphaKlinik Berlin",
      "providerDid": "did:web:alpha-klinik.de:participant",
      "timestamp": "2026-01-22T14:05:00Z",
      "accessCount": 7,
      "policyPurpose": "OMOP CDM analytics for pharmacovigilance and drug safety",
      "policyProhibitedUses": "re-identification,commercial-sale,insurance-decisions,advertising",
      "providerCountry": "DE",
      "providerEdcEndpoint": "https://edc.alpha-klinik.de:8443/api/v1/dsp",
      "negotiationDate": "2026-01-22",
      "lastAccessAt": "2026-03-10T09:15:00Z",
      "contentHash": "9abb1c90a9a7b2252c39e54bd9ad14c2",
      "policyId": "policy:ehds-research-use-53c",
      "contractId": "contract-omop-analytics-002",
      "consumerComplianceEmail": "compliance@pharmaco.de",
      "asset": "OMOP CDM v5.4 Analytics Cohort",
      "consumerDid": "did:web:pharmaco.de:research",
      "policyPermittedUses": "pharmacovigilance,drug-safety,statistics,scientific-research",
      "consumerName": "PharmaCo Research AG",
      "consumerCountry": "DE",
      "status": "FINALIZED"
    },
    {
      "providerCountryCode": "DE",
      "consumerComplianceName": "Thomas Becker",
      "consumerCountryCode": "DE",
      "providerComplianceName": "Dr. Petra Müller",
      "policyRetentionDays": 730,
      "assetId": "dataset:synthea-fhir-r4-mvd",
      "providerComplianceEmail": "dpo@alpha-klinik.de",
      "consumerEdcEndpoint": "https://edc.pharmaco.de:8443/api/v1/dsp",
      "crossBorder": false,
      "policyLegalBasis": "EHDS Art. 53(c) — scientific research",
      "id": "neg-001",
      "policyDataMinimisation": true,
      "accessLogCount": 0,
      "providerName": "AlphaKlinik Berlin",
      "providerDid": "did:web:alpha-klinik.de:participant",
      "timestamp": "2026-01-15T09:12:00Z",
      "accessCount": 4,
      "policyPurpose": "Scientific research on Type 2 Diabetes therapeutic outcomes",
      "policyProhibitedUses": "re-identification,commercial-exploitation,insurance-decisions,marketing",
      "providerCountry": "DE",
      "providerEdcEndpoint": "https://edc.alpha-klinik.de:8443/api/v1/dsp",
      "negotiationDate": "2026-01-15",
      "lastAccessAt": "2026-03-08T14:22:00Z",
      "contentHash": "d544483f68ae2548763e7ca1651c99ca",
      "policyId": "policy:ehds-research-use-53c",
      "contractId": "contract-fhir-t2d-001",
      "consumerComplianceEmail": "compliance@pharmaco.de",
      "asset": "T2D Patient Journey Dataset (FHIR R4)",
      "consumerDid": "did:web:pharmaco.de:research",
      "policyPermittedUses": "scientific-research,statistics,public-health-monitoring,education,ai-training",
      "consumerName": "PharmaCo Research AG",
      "consumerCountry": "DE",
      "status": "CONFIRMED"
    }
  ],
  "credentials": [
    {
      "assessor": "MedReg DE Quality Assessment Unit",
      "assessmentDate": "2025-08-10",
      "conformance": 0.9,
      "format": "VC1_0_JWT",
      "eehrxfCoverage": "full",
      "completeness": 0.88,
      "participant": "Limburg Medical Centre",
      "expiresAt": "2026-09-15T19:28:20.767Z",
      "credentialType": "DataQualityLabelCredential",
      "timeliness": 0.94,
      "issuerDid": "did:web:issuerservice%3A10016:issuer",
      "datasetId": "dataset:prostate-cancer-registry",
      "credentialId": "vc:data-quality-label:clinic-lmc",
      "issuedAt": "2026-03-19T19:28:20.767Z",
      "subjectDid": "did:web:identityhub%3A7083:clinic-lmc",
      "status": "active"
    },
    {
      "assessor": "MedReg DE Quality Assessment Unit",
      "assessmentDate": "2025-07-24",
      "conformance": 0.92,
      "format": "VC1_0_JWT",
      "eehrxfCoverage": "partial",
      "completeness": 0.95,
      "participant": "AlphaKlinik Berlin",
      "expiresAt": "2026-09-15T19:28:20.729Z",
      "credentialType": "DataQualityLabelCredential",
      "timeliness": 0.98,
      "issuerDid": "did:web:issuerservice%3A10016:issuer",
      "datasetId": "dataset:synthea-fhir-r4-mvd",
      "credentialId": "vc:data-quality-label:clinic-alphaklinik",
      "issuedAt": "2026-03-19T19:28:20.729Z",
      "subjectDid": "did:web:identityhub%3A7083:clinic-alphaklinik",
      "status": "active"
    },
    {
      "ehdsArticle": "Article 53",
      "purpose": "Scientific research on therapeutic outcomes",
      "assessor": "",
      "format": "VC1_0_JWT",
      "participant": "PharmaCo Research AG",
      "expiresAt": "2026-06-17T19:28:20.692Z",
      "credentialType": "DataProcessingPurposeCredential",
      "hdabName": "",
      "permittedUses": "scientific-research,statistics,public-health-monitoring,education,ai-training",
      "issuerDid": "did:web:issuerservice%3A10016:issuer",
      "prohibitedUses": "re-identification,commercial-exploitation,insurance-decisions,advertising",
      "credentialId": "vc:data-processing-purpose:cro-pharmaco",
      "validUntil": "2026-06-30",
      "approvalId": "hdab-approval-alpha-klinik-diab",
      "issuedAt": "2026-03-19T19:28:20.692Z",
      "subjectDid": "did:web:identityhub%3A7083:cro-pharmaco",
      "hdabId": "",
      "status": "active"
    },
    {
      "ehdsArticle": "Article 36",
      "jurisdiction": "FR",
      "format": "VC1_0_JWT",
      "participantRole": "HealthDataAccessBody",
      "participant": "Institut de Recherche Santé",
      "expiresAt": "2027-03-19T19:28:20.678Z",
      "credentialType": "EHDSParticipantCredential",
      "hdabName": "Institut de Recherche Santé (IRS FR)",
      "issuerDid": "did:web:issuerservice%3A10016:issuer",
      "registrationDate": "2025-03-15",
      "credentialId": "vc:ehds-participant:hdab-irs",
      "issuedAt": "2026-03-19T19:28:20.678Z",
      "subjectDid": "did:web:identityhub%3A7083:hdab-irs",
      "hdabId": "hdab:irs-fr",
      "status": "active"
    },
    {
      "ehdsArticle": "Article 49",
      "jurisdiction": "NL",
      "format": "VC1_0_JWT",
      "participantRole": "DataHolder",
      "participant": "Limburg Medical Centre",
      "expiresAt": "2027-03-19T19:28:20.662Z",
      "credentialType": "EHDSParticipantCredential",
      "hdabName": "National Medicines Regulatory Authority (MedReg DE)",
      "issuerDid": "did:web:issuerservice%3A10016:issuer",
      "registrationDate": "2025-03-01",
      "credentialId": "vc:ehds-participant:clinic-lmc",
      "issuedAt": "2026-03-19T19:28:20.662Z",
      "subjectDid": "did:web:identityhub%3A7083:clinic-lmc",
      "hdabId": "hdab:medreg-de",
      "status": "active"
    },
    {
      "ehdsArticle": "Article 36",
      "assessor": "",
      "jurisdiction": "DE",
      "format": "VC1_0_JWT",
      "participantRole": "HealthDataAccessBody",
      "participant": "MedReg DE",
      "expiresAt": "2027-03-19T19:28:20.620Z",
      "credentialType": "EHDSParticipantCredential",
      "hdabName": "National Medicines Regulatory Authority (MedReg DE)",
      "issuerDid": "did:web:issuerservice%3A10016:issuer",
      "registrationDate": "2024-06-01",
      "credentialId": "vc:ehds-participant:hdab-medreg",
      "approvalId": "",
      "issuedAt": "2026-03-19T19:28:20.620Z",
      "subjectDid": "did:web:identityhub%3A7083:hdab-medreg",
      "hdabId": "hdab:medreg-de",
      "status": "active"
    },
    {
      "ehdsArticle": "Article 46",
      "assessor": "",
      "jurisdiction": "DE",
      "format": "VC1_0_JWT",
      "participantRole": "DataUser",
      "participant": "PharmaCo Research AG",
      "expiresAt": "2027-03-19T19:28:20.603Z",
      "credentialType": "EHDSParticipantCredential",
      "hdabName": "National Medicines Regulatory Authority (MedReg DE)",
      "issuerDid": "did:web:issuerservice%3A10016:issuer",
      "registrationDate": "2025-02-01",
      "credentialId": "vc:ehds-participant:cro-pharmaco",
      "approvalId": "",
      "issuedAt": "2026-03-19T19:28:20.603Z",
      "subjectDid": "did:web:identityhub%3A7083:cro-pharmaco",
      "hdabId": "hdab:medreg-de",
      "status": "active"
    },
    {
      "ehdsArticle": "Article 49",
      "assessor": "",
      "jurisdiction": "DE",
      "format": "VC1_0_JWT",
      "participantRole": "DataHolder",
      "participant": "AlphaKlinik Berlin",
      "expiresAt": "2027-03-19T19:28:20.559Z",
      "credentialType": "EHDSParticipantCredential",
      "hdabName": "National Medicines Regulatory Authority (MedReg DE)",
      "issuerDid": "did:web:issuerservice%3A10016:issuer",
      "registrationDate": "2025-01-15",
      "credentialId": "vc:ehds-participant:clinic-alphaklinik",
      "approvalId": "",
      "issuedAt": "2026-03-19T19:28:20.559Z",
      "subjectDid": "did:web:identityhub%3A7083:clinic-alphaklinik",
      "hdabId": "hdab:medreg-de",
      "status": "active"
    },
    {
      "credentialType": "MembershipCredential",
      "membershipType": "full",
      "membershipStartDate": "2025-03-15",
      "issuerDid": "did:web:issuerservice%3A10016:issuer",
      "format": "VC1_0_JWT",
      "credentialId": "vc:membership:hdab-irs",
      "membership": "health-dataspace-v2",
      "issuedAt": "2026-03-19T19:28:20.542Z",
      "subjectDid": "did:web:identityhub%3A7083:hdab-irs",
      "participant": "Institut de Recherche Santé",
      "expiresAt": "2027-03-19T19:28:20.542Z",
      "status": "active"
    },
    {
      "credentialType": "MembershipCredential",
      "membershipType": "full",
      "membershipStartDate": "2025-03-01",
      "issuerDid": "did:web:issuerservice%3A10016:issuer",
      "format": "VC1_0_JWT",
      "credentialId": "vc:membership:clinic-lmc",
      "membership": "health-dataspace-v2",
      "issuedAt": "2026-03-19T19:28:20.520Z",
      "subjectDid": "did:web:identityhub%3A7083:clinic-lmc",
      "participant": "Limburg Medical Centre",
      "expiresAt": "2027-03-19T19:28:20.520Z",
      "status": "active"
    },
    {
      "credentialType": "MembershipCredential",
      "membershipType": "full",
      "membershipStartDate": "2024-06-01",
      "issuerDid": "did:web:issuerservice%3A10016:issuer",
      "format": "VC1_0_JWT",
      "credentialId": "vc:membership:hdab-medreg",
      "membership": "health-dataspace-v2",
      "issuedAt": "2026-03-19T19:28:20.504Z",
      "subjectDid": "did:web:identityhub%3A7083:hdab-medreg",
      "participant": "MedReg DE",
      "expiresAt": "2027-03-19T19:28:20.504Z",
      "status": "active"
    },
    {
      "credentialType": "MembershipCredential",
      "membershipType": "full",
      "membershipStartDate": "2025-02-01",
      "issuerDid": "did:web:issuerservice%3A10016:issuer",
      "format": "VC1_0_JWT",
      "credentialId": "vc:membership:cro-pharmaco",
      "membership": "health-dataspace-v2",
      "issuedAt": "2026-03-19T19:28:20.484Z",
      "subjectDid": "did:web:identityhub%3A7083:cro-pharmaco",
      "participant": "PharmaCo Research AG",
      "expiresAt": "2027-03-19T19:28:20.484Z",
      "status": "active"
    },
    {
      "credentialType": "MembershipCredential",
      "membershipType": "full",
      "membershipStartDate": "2025-01-15",
      "issuerDid": "did:web:issuerservice%3A10016:issuer",
      "format": "VC1_0_JWT",
      "credentialId": "vc:membership:clinic-alphaklinik",
      "membership": "health-dataspace-v2",
      "issuedAt": "2026-03-19T19:28:20.336Z",
      "subjectDid": "did:web:identityhub%3A7083:clinic-alphaklinik",
      "participant": "AlphaKlinik Berlin",
      "expiresAt": "2027-03-19T19:28:20.336Z",
      "status": "active"
    }
  ],
  "summary": {
    "nodeCounts": {
      "DataAccessLog": 13,
      "VerifiableCredential": 13,
      "HealthDataset": 5,
      "Participant": 5,
      "ContractNegotiation": 5,
      "DataTransfer": 5
    },
    "accessByConsumer": [
      {
        "consumerName": "PharmaCo Research AG",
        "totalAccesses": 11,
        "totalBytes": 83017600,
        "lastAccess": "2026-03-10T09:15:00Z"
      },
      {
        "consumerName": "MedReg DE",
        "totalAccesses": 2,
        "totalBytes": 10900543,
        "lastAccess": "2026-02-20T11:00:00Z"
      }
    ]
  },
  "participants": [
    {
      "did": "did:web:alpha-klinik.de:participant",
      "name": "AlphaKlinik Berlin",
      "country": "DE",
      "complianceOfficerName": "Dr. Petra Müller",
      "complianceOfficerEmail": "dpo@alpha-klinik.de",
      "complianceOfficerPhone": "+49 30 1234 5678",
      "edcEndpoint": "https://edc.alpha-klinik.de:8443/api/v1/dsp"
    },
    {
      "did": "did:web:irs.fr:hdab",
      "name": "Institut de Recherche Santé",
      "country": "FR",
      "complianceOfficerName": "Dr. Claire Martin",
      "complianceOfficerEmail": "dpo@irs.fr",
      "complianceOfficerPhone": "+33 1 40 51 67 00",
      "edcEndpoint": "https://edc.irs.fr:8443/api/v1/dsp"
    },
    {
      "did": "did:web:lmc.nl:clinic",
      "name": "Limburg Medical Centre",
      "country": "NL",
      "complianceOfficerName": "Ir. Johan van Dijk",
      "complianceOfficerEmail": "fg@lmc.nl",
      "complianceOfficerPhone": "+31 88 459 7000",
      "edcEndpoint": "https://edc.lmc.nl:8443/api/v1/dsp"
    },
    {
      "did": "did:web:medreg.de:hdab",
      "name": "MedReg DE",
      "country": "DE",
      "complianceOfficerName": "Dr. Anneliese Weber",
      "complianceOfficerEmail": "data-governance@medreg.de",
      "complianceOfficerPhone": "+49 228 2070 0",
      "edcEndpoint": "https://edc.medreg.de:8443/api/v1/dsp"
    },
    {
      "did": "did:web:pharmaco.de:research",
      "name": "PharmaCo Research AG",
      "country": "DE",
      "complianceOfficerName": "Thomas Becker",
      "complianceOfficerEmail": "compliance@pharmaco.de",
      "complianceOfficerPhone": "+49 214 9876 5432",
      "edcEndpoint": "https://edc.pharmaco.de:8443/api/v1/dsp"
    }
  ]
}
